{
    "name": "8.0.17-noble",
    "tags": [
        "8.0.17-noble",
        "8.0-noble",
        "8.0.17",
        "8.0"
    ],
    "platforms": [
        "linux/amd64",
        "linux/arm64"
    ],
    "meta": {
        "images": [
            {
                "digest": "sha256:f76c917358b2c4ca1272dd160c82a762408e4e35c8174bf0aede36e7423dbf74",
                "platform": "linux/amd64"
            },
            {
                "digest": "sha256:7b92f374ab4a1cea1043317185e50e2f4be01f9892b74936961797aeb9337888",
                "platform": "linux/arm64"
            }
        ]
    }
}